async_tkinter_loop/__init__.py
async_tkinter_loop/async_tkinter_loop.py
async_tkinter_loop/mixins.py
async_tkinter_loop-0.10.3.dist-info/METADATA
async_tkinter_loop-0.10.3.dist-info/WHEEL
async_tkinter_loop-0.10.3.dist-info/licenses/LICENSE
async_tkinter_loop-0.10.3.dist-info/RECORD
