Metadata-Version: 2.4
Name: async-tkinter-loop
Version: 0.10.3
Summary: Asynchronous mainloop implementation for tkinter
License: MIT
License-File: LICENSE
Keywords: tkinter,async,async-await,asyncio,aiohttp
Author: insolor
Author-email: insolor@gmail.com
Requires-Python: >=3.10,<4.0
Classifier: Development Status :: 4 - Beta
Classifier: Intended Audience :: Developers
Classifier: License :: OSI Approved :: MIT License
Classifier: Operating System :: OS Independent
Classifier: Programming Language :: Python :: 3
Classifier: Programming Language :: Python :: 3.10
Classifier: Programming Language :: Python :: 3.11
Classifier: Programming Language :: Python :: 3.12
Classifier: Programming Language :: Python :: 3.13
Classifier: Programming Language :: Python :: 3.14
Classifier: Topic :: Software Development :: Libraries :: Python Modules
Provides-Extra: examples
Requires-Dist: Pillow (>=10.3.0,<13.0.0) ; extra == "examples"
Requires-Dist: customtkinter (>=5.2.1,<6.0.0) ; extra == "examples"
Requires-Dist: httpx (>=0.23.1,<0.29.0) ; extra == "examples"
Requires-Dist: typing-extensions
Project-URL: Documentation, https://insolor.github.io/async-tkinter-loop/
Project-URL: Homepage, https://github.com/insolor/async-tkinter-loop
Project-URL: Repository, https://github.com/insolor/async-tkinter-loop
